{"assets":{"3CBC34846D10162B9EC9FCD4C3A7BDD8":{"type":"texture","index":0,"url":{"native":"assets\/544093AF-374B-45F5-93E1-6F743C6BE988.pdf"},"width":1920,"height":1080},"9235F2820B530AE44063851E12D9FCC2":{"type":"texture","index":1,"url":{"native":"assets\/544093AF-374B-45F5-93E1-6F743C6BE988.pdf"},"width":1920,"height":1080}},"events":[{"effects":[{"beginTime":0,"baseLayer":{"animations":[],"initialState":{"affineTransform":[1,0,0,1,0,0],"masksToBounds":false,"rotation":0,"scale":1,"position":{"pointX":960,"pointY":540},"width":1920,"sublayerTransform":[1,0,0,0,0,1,0,0,0,0,1,0,0,0,0,1],"contentsRect":{"y":0,"x":0,"width":1,"height":1},"opacity":1,"edgeAntialiasingMask":251658240,"height":1080,"hidden":false,"anchorPoint":{"pointX":0.5,"pointY":0.5}},"objectID":"0","layers":[{"animations":[],"initialState":{"affineTransform":[1,0,0,1,0,0],"masksToBounds":false,"rotation":0,"scale":1,"position":{"pointX":960,"pointY":540},"width":1920,"sublayerTransform":[1,0,0,0,0,1,0,0,0,0,1,-0.00035007912466775983,0,0,0,1],"contentsRect":{"y":0,"x":0,"width":1,"height":1},"opacity":1,"edgeAntialiasingMask":251658240,"height":1080,"hidden":false,"anchorPoint":{"pointX":0.5,"pointY":0.5}},"layers":[{"animations":[],"layers":[],"texturedRectangle":{"isBackgroundTexture":false,"singleTextureOpacity":1,"textureType":0,"textBaseline":0,"textXHeight":0,"isVerticalText":false},"initialState":{"affineTransform":[1,0,0,1,0,0],"masksToBounds":false,"rotation":0,"scale":1,"position":{"pointX":960,"pointY":540},"width":1920,"sublayerTransform":[1,0,0,0,0,1,0,0,0,0,1,0,0,0,0,1],"contentsRect":{"y":0,"x":0,"width":1,"height":1},"opacity":1,"edgeAntialiasingMask":0,"height":1080,"hidden":false,"anchorPoint":{"pointX":0.5,"pointY":0.5}},"texture":"9235F2820B530AE44063851E12D9FCC2"},{"animations":[{"repeatCount":0,"removedOnCompletion":false,"from":{"scalar":1},"timingFunction":"EaseInEaseOut","additive":false,"timeOffset":0,"autoreverses":false,"property":"opacity","fillMode":"both","duration":0.30000001192092896,"beginTime":0,"to":{"scalar":0}}],"layers":[],"texturedRectangle":{"isBackgroundTexture":false,"singleTextureOpacity":1,"textureType":0,"textBaseline":0,"textXHeight":0,"isVerticalText":false},"initialState":{"affineTransform":[1,0,0,1,0,0],"masksToBounds":false,"rotation":0,"scale":1,"position":{"pointX":960,"pointY":540},"width":1920,"sublayerTransform":[1,0,0,0,0,1,0,0,0,0,1,0,0,0,0,1],"contentsRect":{"y":0,"x":0,"width":1,"height":1},"opacity":1,"edgeAntialiasingMask":0,"height":1080,"hidden":false,"anchorPoint":{"pointX":0.5,"pointY":0.5}},"texture":"3CBC34846D10162B9EC9FCD4C3A7BDD8"}]}]},"effects":[],"duration":0.30000001192092896,"type":"transition","attributes":{"direction":0},"name":"apple:dissolve","objectID":"0"}],"automaticPlay":false,"hyperlinks":[{"url":"mailto:m@mario.design","targetRectangle":{"y":1019.5864155888557,"x":348.51821529388428,"width":141.27999999999997,"height":24.915792882442474}}],"accessibility":[{"text":"Developing and Leading Teams","targetRectangle":{"y":107.52956831455231,"x":98.533035278320312,"width":751.39999999999998,"height":54.26398229598999}},{"text":"What I did at Ghost","targetRectangle":{"y":66.096300542354584,"x":101.53303527832031,"width":198.19799633073808,"height":17.975993871688843}},{"text":"pasted-movie.png","targetRectangle":{"y":-6.4999995231628418,"x":1104.7645263671875,"width":1670.5135498046875,"height":1086.5137939453125}},{"text":"Mario Delgado Elysian    􀍖 m@mario.design    􀟝+1 415 683 6861","targetRectangle":{"y":1019.5864155888557,"x":103.72183990478516,"width":561.09247800827018,"height":24.915792882442474}},{"text":"With a commitment to both craft and leadership, I have led design and engineering teams to create products that seamlessly blend functionality and emotional resonance. My leadership fosters a culture of curiosity and collaboration, empowering teams to exceed expectations and deliver extraordinary outcomes.","targetRectangle":{"y":211.98333740234375,"x":104.87763214111328,"width":926.44800000000032,"height":145.96158543243564}},{"text":"Talent Magnet","targetRectangle":{"y":394.4353191928883,"x":104.87763214111328,"width":146.49600000000001,"height":36.511996398449355}},{"text":"I strive to create an environment where vision and purpose attract exceptional talent, inspiring them to do their best work and push the boundaries of what’s possible.","targetRectangle":{"y":430.94731559133766,"x":104.87763214111328,"width":868.96799999999973,"height":109.47118907432673}},{"text":"Culture Lead","targetRectangle":{"y":576.9089010237733,"x":104.87763214111328,"width":132.79199999999997,"height":36.511996398449355}},{"text":"As a leader, I shape company culture by fostering curiosity, collaboration, and a shared commitment to excellence, while creating workspaces that inspire creativity and make people excited to work every day.","targetRectangle":{"y":613.42089742222265,"x":104.87763214111328,"width":917.54399999999987,"height":109.47118907432673}},{"text":"World Class at Any Scale","targetRectangle":{"y":759.38248285465829,"x":104.87763214111328,"width":250.584,"height":36.511996398449355}},{"text":"Whether working solo, with a small team, or within a large organization, I draw on a community of leading-edge investors and innovators to integrate the most forward-thinking methods into my work. Committed to constant learning and improvement, I ensure that every project reflects the latest advancements and delivers meaningful impact.","targetRectangle":{"y":795.89447925310765,"x":104.87763214111328,"width":917.3760000000002,"height":182.45198179054455}}],"baseLayer":{"animations":[],"initialState":{"affineTransform":[1,0,0,1,0,0],"masksToBounds":false,"rotation":0,"scale":1,"position":{"pointX":960,"pointY":540},"width":1920,"sublayerTransform":[1,0,0,0,0,1,0,0,0,0,1,0,0,0,0,1],"contentsRect":{"y":0,"x":0,"width":1,"height":1},"opacity":1,"edgeAntialiasingMask":251658240,"height":1080,"hidden":false,"anchorPoint":{"pointX":0.5,"pointY":0.5}},"objectID":"0","layers":[{"animations":[],"initialState":{"affineTransform":[1,0,0,1,0,0],"masksToBounds":false,"rotation":0,"scale":1,"position":{"pointX":960,"pointY":540},"width":1920,"sublayerTransform":[1,0,0,0,0,1,0,0,0,0,1,-0.00035007912466775983,0,0,0,1],"contentsRect":{"y":0,"x":0,"width":1,"height":1},"opacity":1,"edgeAntialiasingMask":251658240,"height":1080,"hidden":false,"anchorPoint":{"pointX":0.5,"pointY":0.5}},"layers":[{"animations":[],"layers":[],"texturedRectangle":{"isBackgroundTexture":false,"singleTextureOpacity":1,"textureType":0,"textBaseline":0,"textXHeight":0,"isVerticalText":false},"initialState":{"affineTransform":[1,0,0,1,0,0],"masksToBounds":false,"rotation":0,"scale":1,"position":{"pointX":960,"pointY":540},"width":1920,"sublayerTransform":[1,0,0,0,0,1,0,0,0,0,1,0,0,0,0,1],"contentsRect":{"y":0,"x":0,"width":1,"height":1},"opacity":1,"edgeAntialiasingMask":0,"height":1080,"hidden":false,"anchorPoint":{"pointX":0.5,"pointY":0.5}},"texture":"3CBC34846D10162B9EC9FCD4C3A7BDD8"}]}]}}]}